kimmdy_grappa/__init__.py
kimmdy_grappa/grappa_interface.py
kimmdy_grappa-0.4.0.dist-info/licenses/LICENSE
kimmdy_grappa-0.4.0.dist-info/METADATA
kimmdy_grappa-0.4.0.dist-info/WHEEL
kimmdy_grappa-0.4.0.dist-info/entry_points.txt
kimmdy_grappa-0.4.0.dist-info/top_level.txt
kimmdy_grappa-0.4.0.dist-info/RECORD
