Metadata-Version: 2.4
Name: kimmdy-grappa
Version: 0.4.0
Summary: Parameterization interface between KIMMDY and GrAPPa
Author-email: Eric Hartmann <eric.hartmann@h-its.org>
License: GPL-3.0
Classifier: Programming Language :: Python :: 3
Classifier: Operating System :: OS Independent
Requires-Python: >=3.8
License-File: LICENSE
Requires-Dist: kimmdy
Requires-Dist: MDAnalysis
Provides-Extra: dev
Requires-Dist: pytest; extra == "dev"
Requires-Dist: tox; extra == "dev"
Requires-Dist: black; extra == "dev"
Requires-Dist: hypothesis; extra == "dev"
Requires-Dist: jupyter; extra == "dev"
Requires-Dist: griffe<1.0.0,>=0.33; extra == "dev"
Requires-Dist: quartodoc; extra == "dev"
Dynamic: license-file
